__init__.py
cli.py
dnspropagation.py
dnspropagation-0.0.4.dist-info/LICENSE.md
dnspropagation-0.0.4.dist-info/METADATA
dnspropagation-0.0.4.dist-info/WHEEL
dnspropagation-0.0.4.dist-info/entry_points.txt
dnspropagation-0.0.4.dist-info/top_level.txt
dnspropagation-0.0.4.dist-info/RECORD
