Metadata-Version: 2.1
Name: dnspropagation
Version: 0.0.4
Summary: DNS propagation checker
Author-email: Simon Berka <berka@berkasimon.com>
Project-URL: Homepage, https://github.com/berkas1/dnspropagation
Project-URL: Bug Tracker, https://github.com/berkas1/dnspropagation/issues
Classifier: Programming Language :: Python :: 3
Classifier: License :: OSI Approved :: MIT License
Classifier: Operating System :: OS Independent
Requires-Python: >=3.7
License-File: LICENSE.md
Requires-Dist: PyYAML (>=6.0)
Requires-Dist: argcomplete (>=2.0.0)
Requires-Dist: dnspython (>=2.3.0)
Requires-Dist: prettytable (>=3.6.0)
